src/__ini__.py
src/portfoliobuilder.py
portfoliobuilder-0.0.6.dist-info/METADATA
portfoliobuilder-0.0.6.dist-info/WHEEL
portfoliobuilder-0.0.6.dist-info/entry_points.txt
portfoliobuilder-0.0.6.dist-info/top_level.txt
portfoliobuilder-0.0.6.dist-info/zip-safe
portfoliobuilder-0.0.6.dist-info/RECORD
