Metadata-Version: 2.1
Name: portfoliobuilder
Version: 0.0.6
Author: ravinder
Author-email: ravinder.kumar@researchandranking.com
Requires-Dist: click
Requires-Dist: aiohttp
Requires-Dist: requests
